{
    "ctItemsAdded": 15,
    "whenLastItemAdded": "2022-08-06T15:45:38.270Z",
    "ctSaves": 2,
    "whenLastSave": "2022-08-06T15:46:03.689Z",
    "flDirty": false,
    "ctRiverBuilds": 1,
    "whenLastRiverBuild": "2022-08-06T15:46:01.196Z",
    "items": [
        {
            "title": "Service is operating normally: [RESOLVED] Increased Launch Failures",
            "link": "http://status.aws.amazon.com/",
            "description": "Between 6:35 AM and 11:00 AM PDT we experienced increased error rates for new instance launches in the US-EAST-1 Region. Existing instances were unaffected by this issue. By 9:05 AM, we had full recovery in use1-az5. By 10:20 AM, we had full recovery in use1-az6, and at 11:00 AM ...",
            "permalink": "",
            "pubdate": "2022-04-19T18:30:57.000Z",
            "comments": "",
            "feedUrl": "http://status.aws.amazon.com/rss/ec2-us-east-1.rss",
            "when": "2022-08-06T15:45:38.256Z",
            "aggregator": "River5 v0.5.19",
            "id": 155
        },
        {
            "title": "Informational message: Increased Launch Failures",
            "link": "http://status.aws.amazon.com/",
            "description": "We have identified the root cause for increased error rates for new launches in the US-EAST-1 Region. The event affects instances which use EBS Encryption with unencrypted AMIs. Existing instances are not affected. The Availability Zone use1-az5 recovered at 9:05 AM PDT. We ...",
            "permalink": "",
            "pubdate": "2022-04-19T17:46:04.000Z",
            "comments": "",
            "feedUrl": "http://status.aws.amazon.com/rss/ec2-us-east-1.rss",
            "when": "2022-08-06T15:45:38.257Z",
            "aggregator": "River5 v0.5.19",
            "id": 156
        },
        {
            "title": "Informational message: Increased Launch Failures",
            "link": "http://status.aws.amazon.com/",
            "description": "We have identified the root cause for increased error rates for new launches in the US-EAST-1 Region. The event affects instances which use EBS Encryption with unencrypted AMIs. Existing instances are not affected. The Availability Zone use1-az5 recovered at 9:05 AM PDT.  We ...",
            "permalink": "",
            "pubdate": "2022-04-19T17:18:15.000Z",
            "comments": "",
            "feedUrl": "http://status.aws.amazon.com/rss/ec2-us-east-1.rss",
            "when": "2022-08-06T15:45:38.258Z",
            "aggregator": "River5 v0.5.19",
            "id": 157
        },
        {
            "title": "Informational message: Increased Launch Failures",
            "link": "http://status.aws.amazon.com/",
            "description": "We are investigating increased error rates for new launches that use EBS Encryption by Default in the US-EAST-1 Region.  Existing instances are not affected, and no other launch requests are affected. We have identified the root cause.  We are seeing recovery in use1-az5.  We ...",
            "permalink": "",
            "pubdate": "2022-04-19T16:18:38.000Z",
            "comments": "",
            "feedUrl": "http://status.aws.amazon.com/rss/ec2-us-east-1.rss",
            "when": "2022-08-06T15:45:38.259Z",
            "aggregator": "River5 v0.5.19",
            "id": 158
        },
        {
            "title": "Informational message: Increased Launch Failures",
            "link": "http://status.aws.amazon.com/",
            "description": "We are investigating increased error rates for new launches that uses EBS Encryption by Default in the US-EAST-1 Region for three Availability Zones: use1-az2, use1-az6 and use1-az5.  Existing instances are not affected, and no other launch requests are affected.  We have ...",
            "permalink": "",
            "pubdate": "2022-04-19T15:39:31.000Z",
            "comments": "",
            "feedUrl": "http://status.aws.amazon.com/rss/ec2-us-east-1.rss",
            "when": "2022-08-06T15:45:38.260Z",
            "aggregator": "River5 v0.5.19",
            "id": 159
        },
        {
            "title": "Service is operating normally: [RESOLVED] Delayed ENI attachment times",
            "link": "http://status.aws.amazon.com/",
            "description": "Starting at 5:03 PM PDT, we experienced increased ENI attachment times for newly launched EC2 instances and newly attached ENIs within a single Availability Zone  (USE1-AZ4) in the US-EAST-1 Region. The issue was caused by increased resource contention in the subsystem ...",
            "permalink": "",
            "pubdate": "2022-04-01T08:45:11.000Z",
            "comments": "",
            "feedUrl": "http://status.aws.amazon.com/rss/ec2-us-east-1.rss",
            "when": "2022-08-06T15:45:38.261Z",
            "aggregator": "River5 v0.5.19",
            "id": 160
        },
        {
            "title": "Informational message: [RESOLVED] Delayed ENI attachment times",
            "link": "http://status.aws.amazon.com/",
            "description": "ENI network state continues to propagate through the affected Availability Zone (USE1-AZ4) further reducing ENI attachment times. Several affected services - including ELB, Glue and RDS - are now seeing full recovery, while other services - including EMR, EKS, and ECS - are ...",
            "permalink": "",
            "pubdate": "2022-04-01T06:27:58.000Z",
            "comments": "",
            "feedUrl": "http://status.aws.amazon.com/rss/ec2-us-east-1.rss",
            "when": "2022-08-06T15:45:38.262Z",
            "aggregator": "River5 v0.5.19",
            "id": 161
        },
        {
            "title": "Informational message: [RESOLVED] Delayed ENI attachment times",
            "link": "http://status.aws.amazon.com/",
            "description": "While we have continued to make some progress over the last 30 minutes, progress has been slower than expected and ENI attachment times have not yet returned to normal levels within the affected Availability Zone (USE1-AZ4) in the US-EAST-1 Region. ENI network state continues to ...",
            "permalink": "",
            "pubdate": "2022-04-01T05:39:09.000Z",
            "comments": "",
            "feedUrl": "http://status.aws.amazon.com/rss/ec2-us-east-1.rss",
            "when": "2022-08-06T15:45:38.263Z",
            "aggregator": "River5 v0.5.19",
            "id": 162
        },
        {
            "title": "Informational message: [RESOLVED] Delayed ENI attachment times",
            "link": "http://status.aws.amazon.com/",
            "description": "Over the last 15 minutes, we have seen a further improvement in ENI attachment times within the affected Availability Zone (USE1-AZ4) in the US-EAST-1 Region. At these levels, many workflows will operate normally but some may still timeout waiting for full network connectivity ...",
            "permalink": "",
            "pubdate": "2022-04-01T05:04:49.000Z",
            "comments": "",
            "feedUrl": "http://status.aws.amazon.com/rss/ec2-us-east-1.rss",
            "when": "2022-08-06T15:45:38.264Z",
            "aggregator": "River5 v0.5.19",
            "id": 163
        },
        {
            "title": "Informational message: [RESOLVED] Delayed ENI attachment times",
            "link": "http://status.aws.amazon.com/",
            "description": "ENI attachment times continue to take a low number of single digit minutes to establish full network connectivity within the affected Availability Zone (USE1-AZ4) in the US-EAST-1 Region. We do not expect much further improvement until we fully resolve the resource contention ...",
            "permalink": "",
            "pubdate": "2022-04-01T04:31:23.000Z",
            "comments": "",
            "feedUrl": "http://status.aws.amazon.com/rss/ec2-us-east-1.rss",
            "when": "2022-08-06T15:45:38.265Z",
            "aggregator": "River5 v0.5.19",
            "id": 164
        },
        {
            "title": "Informational message: [RESOLVED] Delayed ENI attachment times",
            "link": "http://status.aws.amazon.com/",
            "description": "ENI attachment times continue to take a low number of single digit minutes to establish full network connectivity within the affected Availability Zone (USE1-AZ4) in the US-EAST-1 Region. We do not expect much further improvement until we fully resolve the resource contention ...",
            "permalink": "",
            "pubdate": "2022-04-01T03:58:00.000Z",
            "comments": "",
            "feedUrl": "http://status.aws.amazon.com/rss/ec2-us-east-1.rss",
            "when": "2022-08-06T15:45:38.266Z",
            "aggregator": "River5 v0.5.19",
            "id": 165
        },
        {
            "title": "Informational message: [RESOLVED] Delayed ENI attachment times",
            "link": "http://status.aws.amazon.com/",
            "description": "We continue to see an improvement in ENI attachment times, and while they are getting much closer to normal levels, we're still seeing some ENI attachments take a low number of single digit minutes to establish full network connectivity within the affected Availability Zone ...",
            "permalink": "",
            "pubdate": "2022-04-01T03:23:04.000Z",
            "comments": "",
            "feedUrl": "http://status.aws.amazon.com/rss/ec2-us-east-1.rss",
            "when": "2022-08-06T15:45:38.266Z",
            "aggregator": "River5 v0.5.19",
            "id": 166
        },
        {
            "title": "Informational message: [RESOLVED] Delayed ENI attachment times",
            "link": "http://status.aws.amazon.com/",
            "description": "While ENI attachment times have improved, they are still taking longer than normal in the affected Availability Zone (USE1-AZ4) in the US-EAST-1 Region. The root cause is resource contention within the subsystem responsible for the propagation of network ENI mappings within the ...",
            "permalink": "",
            "pubdate": "2022-04-01T02:47:37.000Z",
            "comments": "",
            "feedUrl": "http://status.aws.amazon.com/rss/ec2-us-east-1.rss",
            "when": "2022-08-06T15:45:38.267Z",
            "aggregator": "River5 v0.5.19",
            "id": 167
        },
        {
            "title": "Informational message: [RESOLVED] Delayed ENI attachment times",
            "link": "http://status.aws.amazon.com/",
            "description": "We are investigating delayed ENI attachment times for EC2 instances within a single Availability Zone (USE1-AZ4) in the US-EAST-1 Region. Newly launched EC2 instances or new ENI attachments, may experience delay in establishing network connectivity within the affected ...",
            "permalink": "",
            "pubdate": "2022-04-01T02:18:08.000Z",
            "comments": "",
            "feedUrl": "http://status.aws.amazon.com/rss/ec2-us-east-1.rss",
            "when": "2022-08-06T15:45:38.268Z",
            "aggregator": "River5 v0.5.19",
            "id": 168
        },
        {
            "title": "Service is operating normally: [RESOLVED] API Error Rates",
            "link": "http://status.aws.amazon.com/",
            "description": "Starting at 4:11 AM PST some EC2 instances and EBS volumes experienced a loss of power in a single data center within a single Availability Zone (USE1-AZ4) in the US-EAST-1 Region. Instances in other data centers within the affected Availability Zone, and other Availability ...",
            "permalink": "",
            "pubdate": "2021-12-23T00:22:00.000Z",
            "comments": "",
            "feedUrl": "http://status.aws.amazon.com/rss/ec2-us-east-1.rss",
            "when": "2022-08-06T15:45:38.269Z",
            "aggregator": "River5 v0.5.19",
            "id": 169
        }
    ]
}